setup.py
salure_helpers/azure/__init__.py
salure_helpers/azure/authentication.py
salure_helpers/azure/azure_connection.py
salure_helpers/azure/blob_storage.py
salure_helpers/azure/entra.py
salure_helpers_azure.egg-info/PKG-INFO
salure_helpers_azure.egg-info/SOURCES.txt
salure_helpers_azure.egg-info/dependency_links.txt
salure_helpers_azure.egg-info/not-zip-safe
salure_helpers_azure.egg-info/requires.txt
salure_helpers_azure.egg-info/top_level.txt