Metadata-Version: 1.0
Name: salure-helpers-azure
Version: 2.0.0
Summary: Azure wrapper from Salure
Home-page: UNKNOWN
Author: D&A Salure
Author-email: support@salureconnnect.com
License: Salure License
Platform: UNKNOWN
